README
setup.py
lz4/__init__.py
lz4/lz4.c
lz4/lz4.h
lz4/lz4frame.c
lz4/lz4frame.h
lz4/lz4frame_static.h
lz4/lz4hc.c
lz4/lz4hc.h
lz4/xxhash.c
lz4/xxhash.h
lz4/__pycache__/_cffi__x4905b62ax4abd53c6.c
lz4/__pycache__/_cffi__x79605bx9444d85.c
lz4/__pycache__/_cffi__xc6a1128bx98342462.c
lz4_cffi.egg-info/PKG-INFO
lz4_cffi.egg-info/SOURCES.txt
lz4_cffi.egg-info/dependency_links.txt
lz4_cffi.egg-info/not-zip-safe
lz4_cffi.egg-info/requires.txt
lz4_cffi.egg-info/top_level.txt